{
  "annotations": { "list": [] },
  "editable": true,
  "fiscalYearStartMonth": 0,
  "graphTooltip": 0,
  "id": null,
  "links": [],
  "liveNow": false,
  "panels": [
    {
      "datasource": { "type": "prometheus", "uid": "prometheus" },
      "fieldConfig": {
        "defaults": {
          "color": { "mode": "palette-classic" },
          "custom": {
            "axisCenteredZero": false,
            "axisColorMode": "text",
            "axisLabel": "",
            "axisPlacement": "auto",
            "drawStyle": "line",
            "fillOpacity": 10,
            "lineWidth": 1
          },
          "unit": "reqps"
        },
        "overrides": []
      },
      "gridPos": { "h": 8, "w": 12, "x": 0, "y": 0 },
      "id": 1,
      "options": { "legend": { "displayMode": "list", "placement": "bottom" } },
      "targets": [
        {
          "datasource": { "type": "prometheus", "uid": "prometheus" },
          "expr": "sum by (route) (rate(http_requests_total[5m]))",
          "legendFormat": "{{route}}",
          "refId": "A"
        }
      ],
      "title": "HTTP RPS by route",
      "type": "timeseries"
    },
    {
      "datasource": { "type": "prometheus", "uid": "prometheus" },
      "fieldConfig": {
        "defaults": {
          "color": { "mode": "palette-classic" },
          "custom": {
            "drawStyle": "line",
            "fillOpacity": 10,
            "lineWidth": 1
          },
          "unit": "s"
        },
        "overrides": []
      },
      "gridPos": { "h": 8, "w": 12, "x": 12, "y": 0 },
      "id": 2,
      "options": { "legend": { "displayMode": "list", "placement": "bottom" } },
      "targets": [
        {
          "datasource": { "type": "prometheus", "uid": "prometheus" },
          "expr": "histogram_quantile(0.95, sum by (le, route) (rate(http_request_duration_seconds_bucket[5m])))",
          "legendFormat": "{{route}} p95",
          "refId": "A"
        }
      ],
      "title": "HTTP latency p95 by route",
      "type": "timeseries"
    },
    {
      "datasource": { "type": "prometheus", "uid": "prometheus" },
      "fieldConfig": {
        "defaults": { "color": { "mode": "thresholds" }, "unit": "none" },
        "overrides": []
      },
      "gridPos": { "h": 6, "w": 12, "x": 0, "y": 8 },
      "id": 3,
      "options": { "orientation": "horizontal", "reduceOptions": { "calcs": ["lastNotNull"] } },
      "targets": [
        {
          "datasource": { "type": "prometheus", "uid": "prometheus" },
          "expr": "diagnostic_reports_total",
          "legendFormat": "diagnostic_reports_total",
          "refId": "A"
        }
      ],
      "title": "Business: diagnostic_reports_total",
      "type": "stat"
    }
  ],
  "refresh": "10s",
  "schemaVersion": 38,
  "style": "dark",
  "tags": ["lab7", "fastapi"],
  "templating": { "list": [] },
  "time": { "from": "now-15m", "to": "now" },
  "timepicker": {},
  "timezone": "browser",
  "title": "Lab 7 — backend",
  "uid": "lab7-backend",
  "version": 1,
  "weekStart": ""
}
